ai_bench/__init__.py
ai_bench/cli.py
ai_bench/harness/__init__.py
ai_bench/harness/core/__init__.py
ai_bench/harness/core/specs.py
ai_bench/harness/runner/__init__.py
ai_bench/harness/runner/kernel_bench_runner.py
ai_bench/harness/testing/__init__.py
ai_bench/harness/testing/timer.py
ai_bench/utils/__init__.py
ai_bench/utils/csv_logger.py
ai_bench/utils/equations.py
ai_bench/utils/finder.py
ai_bench/utils/flop_counter.py
ai_bench/utils/importer.py
ai_bench/utils/logger.py
ai_bench/utils/memory_counter.py
ai_bench_suite-0.2.0b1.dist-info/licenses/LICENSE
ai_bench_suite-0.2.0b1.dist-info/METADATA
ai_bench_suite-0.2.0b1.dist-info/WHEEL
ai_bench_suite-0.2.0b1.dist-info/entry_points.txt
ai_bench_suite-0.2.0b1.dist-info/top_level.txt
ai_bench_suite-0.2.0b1.dist-info/RECORD
