Metadata-Version: 2.4
Name: ai-bench-suite
Version: 0.2.0b1
Summary: AI kernel benchmarking harness
Author-email: Adam Siemieniuk <adam.siemieniuk@intel.com>, Marcin Spoczynski <marcin@spoczynski.com>
License: MIT
Project-URL: Homepage, https://github.com/libxsmm/AI-bench
Project-URL: Repository, https://github.com/libxsmm/AI-bench
Keywords: benchmark,pytorch,triton,helion,gpu,xpu,kernel,performance
Classifier: Development Status :: 4 - Beta
Classifier: Intended Audience :: Developers
Classifier: Intended Audience :: Science/Research
Classifier: License :: OSI Approved :: MIT License
Classifier: Programming Language :: Python :: 3.10
Classifier: Programming Language :: Python :: 3.11
Classifier: Programming Language :: Python :: 3.12
Classifier: Topic :: Scientific/Engineering :: Artificial Intelligence
Classifier: Topic :: System :: Benchmark
Requires-Python: >=3.10
License-File: LICENSE
Requires-Dist: PyYAML
Requires-Dist: numpy
Requires-Dist: python-dotenv
Provides-Extra: cpu
Requires-Dist: torch==2.9.1+cpu; extra == "cpu"
Provides-Extra: xpu
Requires-Dist: torch==2.9.1+xpu; extra == "xpu"
Requires-Dist: pytorch-triton-xpu; extra == "xpu"
Requires-Dist: helion==0.2.9; extra == "xpu"
Dynamic: license-file
